{
  "task_id": "S6FE1",
  "task_name": "로그인 페이지 이메일/비번 폼 + 회원가입/비번찾기 진입로 복원",
  "stage": 6,
  "area": "FE",
  "level": 1,
  "task_status": "Completed",
  "task_progress": 100,
  "verification_status": "Not Verified",
  "dependencies": ["S1SC1", "S4GA1"],
  "priority": "Critical",
  "execution_type": "AI-Only",
  "task_instruction": "바닐라 pages/login.html에는 이메일/비밀번호 로그인 폼, 회원가입 링크, 비밀번호 찾기 링크가 모두 있었으나 React 전환 시 소셜 로그인(Google/Kakao)만 남고 진입로가 누락됨. app/login/page.tsx에 이메일/비번 폼 + /signup + /reset-password 링크 추가. lib/auth.ts에 signInWithEmail() 유틸 추가.",
  "task_agent": "frontend-developer-core",
  "tools": "",
  "generated_files": "app/login/page.tsx (수정), lib/auth.ts (수정)",
  "modification_history": "2026-04-20: 사용자 피드백 — '회원가입 기능조차도 없어'. 원인 조사 결과 /login에서 /signup 진입로 누락 확인. 이메일/비번 폼 복원 + 회원가입/비번찾기 링크 추가.",
  "verification_instruction": "/login 접속 시 이메일/비번 입력 가능, '계정이 없으신가요? 회원가입' 링크 노출, '비밀번호를 잊으셨나요?' 링크 노출 확인. signInWithPassword 호출 시 성공→/ 리디렉션, 실패→한국어 에러 표시.",
  "verification_agent": "code-reviewer-core",
  "test_result": {},
  "build_verification": {},
  "integration_verification": {},
  "blockers": {"count": 0, "items": []},
  "comprehensive_verification": {},
  "notes": "바닐라→React 전환 시 유기적 연결고리 누락 사례. 동일 문제 재발 방지를 위해 S6QA1 E2E 점검 Task 신설.",
  "remarks": "기존 소셜 로그인(Google/Kakao) 버튼은 유지. 이메일 폼이 주(primary), 소셜 로그인은 '또는' 구분선 아래 보조."
}
